spell_checker/__init__.py
spell_checker/dictionary.py
spell_checker/main.py
spell_checker/spellchecker.py
spell_checker/utils.py
spell_checker/dictionaries/english.txt
spell_checker_KERMSHAD-0.1.1.dist-info/LICENSE
spell_checker_KERMSHAD-0.1.1.dist-info/METADATA
spell_checker_KERMSHAD-0.1.1.dist-info/WHEEL
spell_checker_KERMSHAD-0.1.1.dist-info/top_level.txt
spell_checker_KERMSHAD-0.1.1.dist-info/RECORD
