Metadata-Version: 2.1
Name: spell_checker_KERMSHAD
Version: 0.1.1
Summary: Spell checker library
Author: Kermshad
Author-email: Mehrshad Firouzian <mrfirouz007@gmail.com>
Project-URL: Homepage, https://github.com/KH4St3H/spell-checker
Project-URL: Issues, https://github.com/KH4St3H/spell-checker/issues
Classifier: Programming Language :: Python :: 3
Classifier: License :: OSI Approved :: GNU General Public License v3 or later (GPLv3+)
Classifier: Operating System :: OS Independent
Requires-Python: >=3.10
License-File: LICENSE
